bitpin/__init__.py
bitpin/enums.py
bitpin/clients/__init__.py
bitpin/clients/base.py
bitpin/clients/exceptions.py
bitpin/clients/main.py
bitpin/deprecated/__init__.py
bitpin/deprecated/exceptions.py
bitpin/deprecated/helpers.py
bitpin/deprecated/main.py
bitpin-0.4.3.dist-info/METADATA
bitpin-0.4.3.dist-info/WHEEL
bitpin-0.4.3.dist-info/top_level.txt
bitpin-0.4.3.dist-info/RECORD
